[{"title":"影视音乐","nav":[{"title":"在线观看","nav":[{"title":"综合视频","nav":[{"name":"不开VIP.COM","createdAt":"2022-11-05T05:50:07.916Z","rate":5,"desc":"站长自营,界面简洁无广告","top":false,"ownVisible":false,"icon":"http://img.hao502.com/i/2022/11/06/z01ly3.png","url":"http://www.不开vip.com","urls":{}},{"name":"茶杯狐","createdAt":"2022-11-05T05:52:21.428Z","rate":5,"desc":"一个知名度很高的聚合搜索站","top":false,"ownVisible":false,"icon":"http://img.hao502.com/i/2022/11/07/dneaxl.jpeg","url":"https://cupfox.app","urls":{}},{"name":"电影先生","createdAt":"2022-11-05T06:34:52.144Z","rate":4.5,"desc":"目前影视网站模板被模仿者\n永久地址：https://dianying.in/","top":false,"ownVisible":false,"icon":"https://dyxs22.com/favicon.ico","url":"https://dyxs22.com/","urls":{}},{"name":"追剧达人","createdAt":"2022-11-05T05:58:50.487Z","rate":5,"desc":"速度和清晰度不错\n永久地址：https://zjdr.cf","top":false,"ownVisible":false,"icon":"https://vipmv.tv/mxtheme/images/favicon.png","url":"https://zjdr.tv","urls":{}},{"name":"片库","createdAt":"2022-11-05T07:47:58.006Z","rate":4.5,"desc":"支持下载,功能全,更新快\n备用后缀：.org/.to/.nu/.com","top":false,"ownVisible":false,"icon":"https://www.btnull.in/favicon.ico","url":"https://www.btnull.in","urls":{}},{"name":"蛋蛋赞影院","createdAt":"2022-11-08T05:29:55.665Z","rate":4,"desc":"热门影视清晰度和速度都不错","top":false,"ownVisible":false,"icon":"https://www.dandanzan10.top/favicon.ico","url":"https://www.dandanzan10.top/","urls":{}},{"name":"大米星球","createdAt":"2022-11-08T05:19:38.365Z","rate":4,"desc":"热门影视剧清晰度不错\n永久地址：https://www.dmxq.net/","top":false,"ownVisible":false,"icon":"https://ugc.hitv.com/1/22101302373440A2E346E1415C87955C155B224B5Qzkx/dRaWOH0.png","url":"https://www.dmxq.fun/","urls":{}},{"name":"蓝光影院","createdAt":"2022-11-05T07:58:48.362Z","rate":3.5,"desc":"热门影视剧速度和清晰度都不错\n永久地址：https://www.6446.tv/","top":false,"ownVisible":false,"icon":"https://www.lgyy.cc/favicon.ico","url":"https://www.lgyy.cc/","urls":{}},{"name":"COKEMV","createdAt":"2022-11-05T07:42:25.594Z","rate":4.5,"desc":"据说是老站回归,还不错","top":false,"ownVisible":false,"icon":"https://cokemv.me/upload/mxprocms/20221009-1/303f8b904c8401f09153ac65058bad93.png","url":"https://cokemv.me/","urls":{}},{"name":"达达龟影院","createdAt":"2022-11-05T07:10:36.422Z","rate":3.5,"desc":"只支持手机访问\n永久地址：https://www.dadagui.vip/","top":false,"ownVisible":false,"icon":"","url":"https://www.dadagui.me/","urls":{}},{"name":"影视工厂","createdAt":"2022-11-05T06:59:13.687Z","rate":4,"desc":"自建片源,速度不错\n永久地址：https://www.3434.tv","top":false,"ownVisible":false,"icon":"https://www.ysgc.tv/favicon.ico","url":"https://www.ysgc.tv/","urls":{}},{"name":"NOVIPNOAD","createdAt":"2022-11-05T06:54:00.939Z","rate":4,"desc":"没有VIP有AD,速度不错","top":false,"ownVisible":false,"icon":"","url":"https://www.novipnoad.com/","urls":{}},{"name":"LIBVIO在线","createdAt":"2022-11-05T06:51:19.632Z","rate":5,"desc":"热门电影和海外剧,清晰度和速度都不错\n永久地址：https://libvio.app/","top":false,"ownVisible":false,"icon":"https://vkceyugu.cdn.bspapp.com/VKCEYUGU-ae4eabf5-1b15-425e-bdc9-144e48cded99/3ef5af02-735f-4cac-b190-a7695edb1812.ico","url":"https://libvio.me/","urls":{}},{"name":"在线之家","createdAt":"2022-11-05T06:47:26.543Z","rate":5,"desc":"急速播放,只做热门影视剧","top":false,"ownVisible":false,"icon":"https://zxzj.vip/statics/img/favicon.ico","url":"https://zxzj.vip/","urls":{}},{"name":"低端影视","createdAt":"2022-11-05T06:42:11.932Z","rate":5,"desc":"网站风格不随大溜,只更新热门影视","top":false,"ownVisible":false,"icon":"https://ddys.tv/favicon.ico","url":"https://ddys.tv/","urls":{}},{"name":"哔嘀影视","createdAt":"2022-11-05T06:39:18.368Z","rate":5,"desc":"自有片源,资源丰富,速度快\n永久地址：https://www.bdys.me/","top":false,"ownVisible":false,"icon":"https://www.bdys01.com/images/favicon.png","url":"https://www.bdys01.com/","urls":{}},{"name":"555影院","createdAt":"2022-11-05T06:28:28.533Z","rate":4.5,"desc":"有些实力,高清电影电视剧\n永久地址：https://555dy.com/","top":false,"ownVisible":false,"icon":"https://555dy.cc/favicon.ico","url":"https://555dy.cc/","urls":{}}],"collapsed":false,"createdAt":"2021-01-23T01:32:06.423Z","icon":"","ownVisible":null},{"title":"影视APP","nav":[{"name":"美剧范","createdAt":"2022-11-08T05:41:01.267Z","rate":4.5,"desc":"美剧天堂官方APP\n网址：https://mjtt.tv","top":false,"ownVisible":false,"icon":"https://www.meijufan.app/favicon.ico","url":"https://www.meijufan.app/","urls":{}},{"name":"腐剧TV","createdAt":"2022-11-08T05:08:29.059Z","rate":5,"desc":"宅腐资源站官方APP\n网址：https://www.zhaifu.la/","top":false,"ownVisible":false,"icon":"https://www.fuju.app/favicon.ico","url":"https://www.fuju.app/","urls":{}},{"name":"特狗影视","createdAt":"2022-11-08T02:54:50.680Z","rate":5,"desc":"站长自用APP,目前只剩安卓端","top":false,"ownVisible":false,"icon":"https://www.tegouys.com/logo.png","url":"https://www.tegouys.com/","urls":{}},{"name":"极光影院","createdAt":"2022-11-08T02:35:40.721Z","rate":4.5,"desc":"手机电视双端,据说电视版无广告","top":false,"ownVisible":false,"icon":null,"url":"https://pan.bilnn.com/s/rqyBha?path=%2F","urls":{}},{"name":"TVBox","createdAt":"2022-11-08T02:34:19.187Z","rate":4,"desc":"聚合视频,电视盒子用","top":false,"ownVisible":false,"icon":"https://wwt.lanzouw.com/favicon.ico","url":"https://wwt.lanzouw.com/if1Bx0c0x7sb","urls":{}},{"name":"影视酷","createdAt":"2022-11-08T02:03:30.785Z","rate":4,"desc":"比较小巧的一款APP","top":false,"ownVisible":false,"icon":"https://wwt.lanzouw.com/favicon.ico","url":"https://wwt.lanzouw.com/yingshiku","urls":{}},{"name":"美剧巴士","createdAt":"2022-11-08T02:02:21.015Z","rate":4.5,"desc":"海外影视剧,速度快清晰度高","top":false,"ownVisible":false,"icon":"https://wwt.lanzouw.com/favicon.ico","url":"https://wwt.lanzouw.com/mjbsdown","urls":{}},{"name":"影视森林","createdAt":"2022-11-08T02:01:23.529Z","rate":4.5,"desc":"据APP开发者说很良心","top":false,"ownVisible":false,"icon":"https://wwt.lanzouw.com/favicon.ico","url":"https://wwt.lanzouw.com/senlins","urls":{}},{"name":"V视频","createdAt":"2022-11-08T02:00:25.351Z","rate":5,"desc":"免费无广告,清晰度好速度快","top":false,"ownVisible":false,"icon":"https://www.vyins.app/favicon.ico","url":"https://www.vyins.app/","urls":{}},{"name":"韩剧鸟","createdAt":"2022-11-08T01:58:33.078Z","rate":4.5,"desc":"据说无广告","top":false,"ownVisible":false,"icon":"https://wwe.lanzouw.com/favicon.ico","url":"https://wwe.lanzouw.com/hanjuniao","urls":{}}],"collapsed":false,"createdAt":"2021-01-23T01:32:06.423Z","icon":"","ownVisible":null},{"createdAt":"2022-11-05T08:23:35.244Z","title":"日韩剧","icon":"","ownVisible":null,"nav":[]},{"createdAt":"2022-11-05T08:23:24.097Z","title":"美剧","icon":"","ownVisible":null,"nav":[{"name":"91美剧网","createdAt":"2022-11-08T05:26:42.009Z","rate":3.5,"desc":"提供美剧下载和播放,手机广告体验不好\n永久域名：https://www.91mjtt.cc/","top":false,"ownVisible":false,"icon":"https://91mjtt.cc/favicon.ico","url":"https://91mjtt.cc/","urls":{}},{"name":"美剧天堂","createdAt":"2022-11-08T02:50:10.312Z","rate":5,"desc":"美剧下载第一站,支持在线播放\n永久域名：https://www.mjtt.tv/","top":false,"ownVisible":false,"icon":"https://www.meijutt.net/favicon.ico","url":"https://www.meijutt.net/","urls":{}},{"name":"4K鸭","createdAt":"2022-11-05T08:36:00.937Z","rate":5,"desc":"目前只做Netflix和Youtobe\n永久地址：https://azx.me/","top":false,"ownVisible":false,"icon":"https://yanetflix.com/favicon.ico","url":"https://yanetflix.com/","urls":{}}]},{"createdAt":"2022-11-05T08:24:04.675Z","title":"动漫","icon":"","ownVisible":null,"nav":[{"name":"ZzzFun","createdAt":"2022-11-05T08:35:23.419Z","rate":5,"desc":"网站UI不错,支持弹幕,速度快","top":false,"ownVisible":false,"icon":null,"url":"http://www.zzzfun.com/","urls":{}},{"name":"AGE动漫","createdAt":"2022-11-05T08:34:45.008Z","rate":4.5,"desc":"番剧内容丰富\n备用地址：https;//www.age.tv","top":false,"ownVisible":false,"icon":"https://www.agemys.net/favicon.ico","url":"https://www.agemys.net/","urls":{}},{"name":"Z动漫","createdAt":"2022-11-05T08:34:06.852Z","rate":4,"desc":"专注动漫的视频网站","top":false,"ownVisible":false,"icon":"https://www.dm2022.com/mxtheme/images/favicon.png","url":"https://www.dm2022.com/","urls":{}}]},{"createdAt":"2022-11-05T08:27:54.414Z","title":"其他","icon":null,"ownVisible":null,"nav":[{"name":"MVCAT","createdAt":"2022-11-08T05:24:40.195Z","rate":5,"desc":"影视推荐站","top":false,"ownVisible":false,"icon":"","url":"https://www.mvcat.com/","urls":{}}]}],"collapsed":false,"createdAt":"2021-01-23T01:32:06.423Z","icon":"","ownVisible":null},{"createdAt":"2022-11-05T08:22:01.916Z","title":"影视下载","icon":null,"ownVisible":null,"nav":[{"createdAt":"2022-11-08T02:43:28.927Z","title":"影视下载","icon":null,"ownVisible":null,"nav":[{"name":"皮皮虾资源","createdAt":"2022-11-08T05:15:52.506Z","rate":4.5,"desc":"主要是网盘资源,广告比较少","top":false,"ownVisible":false,"icon":"https://img30.360buyimg.com/pop/jfs/t1/186346/14/15177/7551/61043dbeE6d97d4a0/7660dbdc14f8509d.png","url":"https://ppxzy.co/","urls":{}},{"name":"新剧场","createdAt":"2022-11-08T05:11:55.743Z","rate":4.5,"desc":"百度云影视下载站","top":false,"ownVisible":false,"icon":"https://www.xinjuc.com/wp-content/uploads/2021/12/logo1.png","url":"https://www.xinjuc.com/","urls":{}},{"name":"比特大雄","createdAt":"2022-11-08T05:10:25.395Z","rate":5,"desc":"老牌下载站,资源丰富","top":false,"ownVisible":false,"icon":"https://www.btdx8.com/favicon.ico","url":"https://www.btdx8.com/","urls":{}},{"name":"凑新资源","createdAt":"2022-11-08T05:03:47.029Z","rate":4,"desc":"很多经典老剧,手机不适应","top":false,"ownVisible":false,"icon":"http://65co.co/favicon.ico","url":"http://65co.co/","urls":{}},{"name":"人人影视下载分享","createdAt":"2022-11-08T04:59:11.794Z","rate":4.5,"desc":"应该是爬了之前人人的数据,资源挺全","top":false,"ownVisible":false,"icon":"https://yyets.dmesg.app/favicon.ico","url":"https://yyets.dmesg.app/home","urls":{}},{"name":"YYDS电影","createdAt":"2022-11-08T04:10:14.693Z","rate":4,"desc":"所有资源都是百度云下载","top":false,"ownVisible":false,"icon":"https://shp.qpic.cn/collector/1523230910/10d6b04e-e7a8-4db1-92ae-5b53518ab9f8/0","url":"https://yyds.fans/","urls":{}},{"name":"音范丝","createdAt":"2022-11-08T04:06:50.722Z","rate":4,"desc":"主打蓝光和4K下载","top":false,"ownVisible":false,"icon":"https://www.yinfans.me/wp-content/themes/Loos2/images/favicon.ico","url":"https://www.yinfans.me/","urls":{}},{"name":"电影天堂","createdAt":"2022-11-08T03:21:47.449Z","rate":3.5,"desc":"老牌下载站","top":false,"ownVisible":false,"icon":"https://dytt8.net/favicon.ico","url":"https://dytt8.net/","urls":{}},{"name":"BT吧","createdAt":"2022-11-08T03:17:16.369Z","rate":3,"desc":"只支持电脑下载\n永久域名：https://www.btba.com.cn/","top":false,"ownVisible":false,"icon":null,"url":"https://www.aibtba.com/","urls":{}},{"name":"CHAOSPACE","createdAt":"2022-11-08T02:46:09.375Z","rate":4,"desc":"高清压制无广告,需付费注册","top":false,"ownVisible":false,"icon":"https://www.chaospace.fun/wp-content/uploads/2020/06/favicon.ico","url":"https://www.chaospace.fun/","urls":{}},{"name":"悠悠MP4","createdAt":"2022-11-08T02:45:03.483Z","rate":3,"desc":"界面不咋滴","top":false,"ownVisible":false,"icon":"https://www.uump4.net/favicon.png","url":"https://www.uump4.net/","urls":{}}]},{"createdAt":"2022-11-08T03:54:53.459Z","title":"特色下载","icon":null,"ownVisible":null,"nav":[{"name":"盗火纪录片","createdAt":"2022-11-08T05:32:34.398Z","rate":4,"desc":"纪录片下载网站,提供百度云和迅雷","top":false,"ownVisible":false,"icon":"","url":"http://www.daofire.com/","urls":{}},{"name":"宅腐资源站","createdAt":"2022-11-08T05:05:43.735Z","rate":4,"desc":"腐宅影视剧","top":false,"ownVisible":false,"icon":"https://www.zhaifu.la/favicon.ico","url":"https://www.zhaifu.la/","urls":{}},{"name":"漫猫动漫BT下载","createdAt":"2022-11-08T05:01:50.222Z","rate":4,"desc":"番剧日剧下载,更新比较快","top":false,"ownVisible":false,"icon":"http://www.comicat.org/images/favicon/comicat.ico","url":"http://www.comicat.org/","urls":{}},{"name":"ACG动漫","createdAt":"2022-11-08T04:57:13.498Z","rate":4,"desc":"专业动漫下载网站","top":false,"ownVisible":false,"icon":"https://acg.rip/favicon.ico","url":"https://acg.rip/","urls":{}},{"name":"韩饭网","createdAt":"2022-11-08T04:55:32.894Z","rate":4,"desc":"韩剧下载,提供BT和百度云","top":false,"ownVisible":false,"icon":null,"url":"https://www.hanfan.cc/","urls":{}},{"name":"我爱ABC","createdAt":"2022-11-08T04:07:57.149Z","rate":4,"desc":"少儿早教动画站,中英文","top":false,"ownVisible":false,"icon":null,"url":"https://www.oiabc.com/","urls":{}},{"name":"追新番","createdAt":"2022-11-08T03:59:29.559Z","rate":4,"desc":"日剧主要资源站,手机体验不好","top":false,"ownVisible":false,"icon":null,"url":"http://www.fanxinzhui.com/","urls":{}},{"name":"心动日剧","createdAt":"2022-11-08T03:58:36.454Z","rate":3.5,"desc":"访问速度不佳,据说是日剧最全的资源站,下载需积分","top":false,"ownVisible":false,"icon":null,"url":"http://www.doki8.com/","urls":{}},{"name":"日剧跑","createdAt":"2022-11-08T03:58:01.175Z","rate":4,"desc":"日剧资源丰富","top":false,"ownVisible":false,"icon":"https://www.rijupao.com/favicon.ico","url":"https://www.rijupao.com/","urls":{}},{"name":"泰剧资料馆","createdAt":"2022-11-08T03:57:25.595Z","rate":4.5,"desc":"专门的泰剧百度云下载站,资源丰富","top":false,"ownVisible":false,"icon":"https://www.taijuzlg.com/favicon.ico","url":"https://www.taijuzlg.com/","urls":{}},{"name":"蜜柑计划","createdAt":"2022-11-08T03:56:37.339Z","rate":5,"desc":"番剧下载站,更新及时","top":false,"ownVisible":false,"icon":"https://mikanani.me/favicon.ico","url":"https://mikanani.me/","urls":{}}]},{"createdAt":"2022-11-08T04:12:06.247Z","title":"下载论坛","icon":null,"ownVisible":null,"nav":[{"name":"战火影视","createdAt":"2022-11-08T05:38:48.229Z","rate":4,"desc":"战争类影视下载论坛","top":false,"ownVisible":false,"icon":null,"url":"http://www.zhys.66rt.com/","urls":{}},{"name":"诺曼底影视","createdAt":"2022-11-08T05:37:47.537Z","rate":4,"desc":"战争类影视剧下载论坛","top":false,"ownVisible":false,"icon":"","url":"http://www.nmandy.com/","urls":{}},{"name":"下载001","createdAt":"2022-11-08T04:13:33.609Z","rate":4,"desc":"资源整理的不错","top":false,"ownVisible":false,"icon":"https://www.xiazai001.com/favicon.ico","url":"https://www.xiazai001.com/","urls":{}}]}]},{"title":"磁力/网盘","nav":[{"createdAt":"2022-11-08T05:42:01.827Z","title":"网盘搜索","icon":null,"ownVisible":null,"nav":[{"name":"找资源","createdAt":"2022-11-18T13:22:56.620Z","rate":5,"desc":"阿里云盘资源搜索引擎","top":false,"ownVisible":false,"icon":"https://zhaoziyuan.la/favicon.ico","url":"https://zhaoziyuan.la/","urls":{}},{"name":"TG中文搜索","createdAt":"2022-11-08T06:30:02.014Z","rate":4,"desc":"电报搜索站","top":false,"ownVisible":false,"icon":"https://meow.tg/favicon.ico","url":"https://meow.tg/","urls":{}},{"name":"小马盘","createdAt":"2022-11-08T06:26:56.201Z","rate":4,"desc":"需关注公众号","top":false,"ownVisible":false,"icon":"https://www.xiaomapan.com/favicon.ico","url":"https://www.xiaomapan.com/","urls":{}},{"name":"橘子盘搜","createdAt":"2022-11-08T06:25:24.190Z","rate":5,"desc":"据说特别好用","top":false,"ownVisible":false,"icon":"https://www.nmme.cc/favicon.ico","url":"https://www.nmme.cc/","urls":{}},{"name":"奈斯搜索","createdAt":"2022-11-08T06:16:38.728Z","rate":4.5,"desc":"阿里云盘搜索,无广告需登录","top":false,"ownVisible":false,"icon":"https://www.niceso.fun/favicon.ico","url":"https://www.niceso.fun/","urls":{}},{"name":"UP云搜","createdAt":"2022-11-08T06:15:43.636Z","rate":5,"desc":"阿里云盘搜索站,简单无套路","top":false,"ownVisible":false,"icon":"https://www.upyunso.com/static/img/upso_mlogo.png","url":"https://www.upyunso.com/","urls":{}},{"name":"优聚搜","createdAt":"2022-11-08T06:13:41.518Z","rate":5,"desc":"阿里云盘搜索站","top":false,"ownVisible":false,"icon":"https://jujuso.com/favicon.ico","url":"https://jujuso.com/","urls":{}},{"name":"盘么么","createdAt":"2022-11-08T06:12:04.644Z","rate":4,"desc":"和盘58、热盘搜等属同一家","top":false,"ownVisible":false,"icon":null,"url":"http://www.panmeme.com/","urls":{}},{"name":"热盘搜","createdAt":"2022-11-08T06:00:39.397Z","rate":4.5,"desc":"挺不错的百度云搜索站","top":false,"ownVisible":false,"icon":"","url":"http://www.repanso.com/","urls":{}}]},{"createdAt":"2022-11-08T05:41:50.808Z","title":"磁力搜索","icon":null,"ownVisible":null,"nav":[{"name":"海盗湾","createdAt":"2022-11-08T05:58:02.679Z","rate":4,"desc":"号称全球最大BT网站","top":false,"ownVisible":false,"icon":"https://piratebayproxy.info/favicon.ico","url":"https://piratebayproxy.info/","urls":{}},{"name":"Nyaa","createdAt":"2022-11-08T05:56:37.309Z","rate":4,"desc":"番剧头部站","top":false,"ownVisible":false,"icon":null,"url":"https://nyaa.si/","urls":{}},{"name":"Zooqle","createdAt":"2022-11-08T05:55:06.252Z","rate":4,"desc":"各种海外影视剧下载","top":false,"ownVisible":false,"icon":null,"url":"https://zooqle.com/","urls":{}},{"name":"RuTracker","createdAt":"2022-11-08T05:52:30.013Z","rate":4,"desc":"俄罗斯官方授权BT站","top":false,"ownVisible":false,"icon":"http://rutracker.org/favicon.ico","url":"http://rutracker.org/","urls":{}},{"name":"磁力猫","createdAt":"2022-11-08T05:51:07.582Z","rate":3.5,"desc":"磁力搜索站\n备用地址：http://cilimao.biz/","top":false,"ownVisible":false,"icon":"","url":"http://clm.la/","urls":{}},{"name":"EZTV","createdAt":"2022-11-08T05:45:29.633Z","rate":3.5,"desc":"一手美剧资源,无字幕无中文","top":false,"ownVisible":false,"icon":"https://eztv.re/favicon.ico","url":"https://eztv.re/","urls":{}},{"name":"动漫花园","createdAt":"2022-11-08T05:44:41.532Z","rate":3.5,"desc":"番剧很丰富,更新快","top":false,"ownVisible":false,"icon":"https://share.dmhy.org/favicon.ico","url":"https://share.dmhy.org/","urls":{}}]}],"createdAt":"2021-01-23T01:32:06.423Z","icon":"","ownVisible":null},{"title":"字幕/解析","nav":[{"createdAt":"2022-11-08T07:05:57.396Z","title":"解析接口","icon":null,"ownVisible":null,"nav":[{"name":"虾米解析","createdAt":"2022-11-18T11:32:14.297Z","rate":4.5,"desc":"免费解析,应该带广告","top":false,"ownVisible":false,"icon":"","url":"https://jx.xmflv.com/?url=","urls":{}},{"name":"OK解析","createdAt":"2022-11-18T11:28:39.761Z","rate":4.5,"desc":"免费解析,应该带广告","top":false,"ownVisible":false,"icon":"https://okjx.cc/favicon.ico","url":"https://okjx.cc/?url=","urls":{}},{"name":"8090解析","createdAt":"2022-11-14T12:15:07.273Z","rate":4,"desc":"免费官方解析,带广告","top":false,"ownVisible":false,"icon":"https://www.8090g.cn/favicon.ico","url":"https://www.8090g.cn/jiexi/?url=","urls":{}},{"name":"鸿途解析","createdAt":"2022-11-08T08:24:05.951Z","rate":4,"desc":"免费json解析","top":false,"ownVisible":false,"icon":null,"url":"http://www.freejson.xyz/","urls":{}},{"name":"诺讯解析","createdAt":"2022-11-08T07:23:36.833Z","rate":5,"desc":"诺讯系统官方解析","top":false,"ownVisible":false,"icon":"https://vip.nxflv.com/favicon.ico","url":"https://vip.nxflv.com/","urls":{}},{"name":"BL解析","createdAt":"2022-11-08T07:10:06.542Z","rate":4,"desc":"官方解析,支持个人用户","top":false,"ownVisible":false,"icon":"https://svip.bljiex.cc/favicon.ico","url":"https://svip.bljiex.cc/","urls":{}},{"name":"思古解析","createdAt":"2022-11-08T07:28:12.592Z","rate":5,"desc":"付费解析","top":false,"ownVisible":false,"icon":"https://api.gbxy.net.cn/favicon.ico","url":"https://api.gbxy.net.cn/","urls":{}},{"name":"冰豆解析","createdAt":"2022-11-08T07:14:10.073Z","rate":4,"desc":"免费官方解析,带广告,域名有点东西","top":false,"ownVisible":false,"icon":"https://bd.jx.cn/favicon.ico","url":"https://bd.jx.cn/?url=","urls":{}},{"name":"麒麟解析","createdAt":"2022-11-08T07:21:08.056Z","rate":5,"desc":"付费解析","top":false,"ownVisible":false,"icon":"https://svip.qljx.top/favicon.ico","url":"https://svip.qljx.top/","urls":{}},{"name":"爱酷解析","createdAt":"2022-11-08T08:16:26.050Z","rate":4,"desc":"付费解析","top":false,"ownVisible":false,"icon":"https://json.icu/favicon.ico","url":"https://json.icu/","urls":{}},{"name":"小猫咪解析","createdAt":"2022-11-08T07:34:25.090Z","rate":4,"desc":"付费解析","top":false,"ownVisible":false,"icon":null,"url":"http://vip.xiaomaomi.tv/","urls":{}},{"name":"茶语解析","createdAt":"2022-11-08T08:18:00.949Z","rate":4,"desc":"付费解析","top":false,"ownVisible":false,"icon":"https://cy.myjx.work/favicon.ico","url":"https://cy.myjx.work/","urls":{}}]},{"createdAt":"2022-11-08T07:06:09.302Z","title":"字幕组","icon":null,"ownVisible":null,"nav":[{"name":"字幕库","createdAt":"2022-11-08T08:56:59.927Z","rate":4,"desc":"字幕聚合站","top":false,"ownVisible":false,"icon":"","url":"https://zmk.pw/","urls":{}},{"name":"东京不够热","createdAt":"2022-11-08T08:32:26.160Z","rate":5,"desc":"日本影视资源为主","top":false,"ownVisible":false,"icon":"https://www.tnhsub.com/wp-content/uploads/2019/06/cropped-favicon-32x32.png","url":"https://www.tnhsub.com/","urls":{}},{"name":"NEW字幕组","createdAt":"2022-11-08T08:47:09.120Z","rate":4.5,"desc":"翻译快,没广告","top":false,"ownVisible":false,"icon":"https://newzmz.com/favicon.ico","url":"https://newzmz.com/","urls":{}},{"name":"树屋字幕组","createdAt":"2022-11-08T08:54:45.572Z","rate":4,"desc":"很多稀缺资源,产量不高,质量不错","top":false,"ownVisible":false,"icon":null,"url":"http://treehousesub.com/","urls":{}},{"name":"神叨字幕组","createdAt":"2022-11-08T08:52:41.565Z","rate":4,"desc":"韩剧字幕组,产量不高,无广告\n论坛生日：150326","top":false,"ownVisible":false,"icon":"","url":"http://www.shenbibi.com/","urls":{}},{"name":"漫迪字幕组","createdAt":"2022-11-08T08:50:13.504Z","rate":5,"desc":"漫迪字幕组所有动漫作品合集,无广告","top":false,"ownVisible":false,"icon":null,"url":"https://mdsub.tk/","urls":{}},{"name":"FIX字幕侠","createdAt":"2022-11-08T08:45:46.851Z","rate":4.5,"desc":"语种多,广告少,更新快","top":false,"ownVisible":false,"icon":"https://www.zimuxia.cn/favicon.ico","url":"https://www.zimuxia.cn/","urls":{}},{"name":"人人影视字幕组","createdAt":"2022-11-08T08:28:19.048Z","rate":5,"desc":"人人影视原班人马,只提供字幕不提供片源","top":false,"ownVisible":false,"icon":"https://www.yysub.net/favicon.ico","url":"https://www.yysub.net/","urls":{}},{"name":"韩迷字幕组","createdAt":"2022-11-08T08:43:45.322Z","rate":4,"desc":"压片加了广告","top":false,"ownVisible":false,"icon":null,"url":"http://www.hanmi520.com/","urls":{}},{"name":"弯弯字幕组","createdAt":"2022-11-08T08:41:58.609Z","rate":4,"desc":"语种比较多","top":false,"ownVisible":false,"icon":null,"url":"http://wanwansub.com/","urls":{}},{"name":"深影字幕组","createdAt":"2022-11-08T08:40:34.016Z","rate":4,"desc":"美剧字幕组,论坛形式","top":false,"ownVisible":false,"icon":"https://forum.shinybbs.vip/favicon.ico","url":"https://forum.shinybbs.vip/","urls":{}},{"name":"冰冰字幕组","createdAt":"2022-11-08T08:37:34.461Z","rate":4,"desc":"主要翻译一些小众剧","top":false,"ownVisible":false,"icon":"https://www.icezmz.com/favicon.ico","url":"https://www.icezmz.com/","urls":{}},{"name":"亿万同人字幕组","createdAt":"2022-11-08T08:35:10.882Z","rate":3.5,"desc":"主要翻译LGBTQ类型的剧","top":false,"ownVisible":false,"icon":null,"url":"http://ywtrzm.com/","urls":{}},{"name":"Subscene","createdAt":"2022-11-08T08:30:07.045Z","rate":4,"desc":"英文字幕","top":false,"ownVisible":false,"icon":"https://subscene.com/favicon.ico","url":"https://subscene.com/","urls":{}},{"name":"TLF字幕组","createdAt":"2022-11-08T08:27:12.591Z","rate":4,"desc":"比较早期的字幕组","top":false,"ownVisible":false,"icon":"https://sub.eastgame.org/favicon.ico","url":"https://sub.eastgame.org/","urls":{}},{"name":"SubHD","createdAt":"2022-11-08T08:26:07.637Z","rate":4,"desc":"欧美剧字幕聚合站","top":false,"ownVisible":false,"icon":null,"url":"https://subhd.tv/","urls":{}}]}],"createdAt":"2021-01-23T01:32:06.423Z","icon":"","ownVisible":null},{"title":"资源采集","nav":[{"createdAt":"2022-11-08T09:06:36.094Z","title":"采集站","icon":null,"ownVisible":null,"nav":[{"name":"天堂资源","createdAt":"2022-11-08T09:36:36.151Z","rate":5,"desc":"免费官方资源采集站","top":false,"ownVisible":false,"icon":"","url":"http://vipmv.cc/","urls":{}},{"name":"麒麟资源站","createdAt":"2022-11-08T09:35:20.936Z","rate":5,"desc":"比较良心的官方资源站","top":false,"ownVisible":false,"icon":null,"url":"https://qilinzyz.com/","urls":{}},{"name":"天空资源","createdAt":"2022-11-08T09:27:04.717Z","rate":4.5,"desc":"备用：https://tkzy1.com/","top":false,"ownVisible":false,"icon":null,"url":"https://tiankongzy.com/","urls":{}},{"name":"U酷资源","createdAt":"2022-11-08T09:24:19.597Z","rate":5,"desc":"备用：https://ukuzy1.com/","top":false,"ownVisible":false,"icon":null,"url":"https://ukuzy0.com/","urls":{}},{"name":"百度资源","createdAt":"2022-11-08T09:23:09.713Z","rate":5,"desc":"备用：https://www.bdzy.com/","top":false,"ownVisible":false,"icon":null,"url":"https://bdyunzy.com/","urls":{}},{"name":"ikun资源","createdAt":"2022-11-08T09:21:11.576Z","rate":5,"desc":"小黑子专用","top":false,"ownVisible":false,"icon":"https://ikunzy.com/favicon.ico","url":"https://ikunzy.com/","urls":{}},{"name":"优质资源","createdAt":"2022-11-08T09:18:50.208Z","rate":4.5,"desc":"备用：https://1080zyk1.com/","top":false,"ownVisible":false,"icon":"https://1080zyk.com/favicon.ico","url":"https://1080zyk.com/","urls":{}},{"name":"无尽资源","createdAt":"2022-11-08T09:12:25.236Z","rate":5,"desc":"备用：https://www.wujinzy.com/","top":false,"ownVisible":false,"icon":null,"url":"https://www.wujinzy.net/","urls":{}},{"name":"红牛资源","createdAt":"2022-11-08T09:11:03.919Z","rate":5,"desc":"备用：https://hongniuziyuan.com/","top":false,"ownVisible":false,"icon":null,"url":"https://hongniuziyuan.net/","urls":{}}]},{"createdAt":"2022-11-08T09:06:43.520Z","title":"其他","icon":null,"ownVisible":null,"nav":[{"name":"苹果CMS使用手册","createdAt":"2022-11-08T09:44:46.174Z","rate":5,"desc":"很实用的一个手册,非本人撰写","top":false,"ownVisible":false,"icon":"https://www.showdoc.com.cn/favicon.ico","url":"https://www.showdoc.com.cn/mytheme?page_id=2779989134071820","urls":{}},{"name":"萌芽采集插件","createdAt":"2022-11-08T09:40:48.906Z","rate":4.5,"desc":"苹果CMS采集插件,用户量应该不低","top":false,"ownVisible":false,"icon":"","url":"https://www.mycj.pro/","urls":{}},{"name":"逮虾户","createdAt":"2022-11-08T09:39:34.122Z","rate":4.5,"desc":"各种海外平台账号出售","top":false,"ownVisible":false,"icon":"https://daixiahu.co/favicon.png","url":"https://daixiahu.co/#/buses","urls":{}}]}],"createdAt":"2021-01-23T01:32:06.423Z","icon":"","ownVisible":null},{"title":"音乐相关","nav":[{"createdAt":"2022-11-08T09:56:52.671Z","title":"音乐资源","icon":null,"ownVisible":null,"nav":[{"name":"音乐磁场","createdAt":"2022-11-08T10:11:14.446Z","rate":5,"desc":"音乐分享论坛,活跃度很高","top":false,"ownVisible":false,"icon":"https://www.hifini.com/favicon.ico","url":"https://www.hifini.com/","urls":{}},{"name":"音乐搜索器","createdAt":"2022-11-08T09:59:04.199Z","rate":4,"desc":"音乐聚合搜索站","top":false,"ownVisible":false,"icon":null,"url":"http://www.musictool.top/","urls":{}},{"name":"下歌吧","createdAt":"2022-11-08T09:57:52.953Z","rate":4,"desc":"支持在线播放和下载,免费","top":false,"ownVisible":false,"icon":"https://music.y444.cn/favicon.ico","url":"https://music.y444.cn/","urls":{}}]}],"createdAt":"2021-01-23T01:32:06.423Z","icon":"","ownVisible":null}],"id":0,"createdAt":"2021-01-23T01:32:06.423Z","icon":"","ownVisible":null},{"createdAt":"2022-11-08T01:55:31.568Z","title":"站长相关","icon":null,"ownVisible":null,"nav":[{"createdAt":"2022-11-08T01:56:13.174Z","title":"IDC/服务器","icon":null,"ownVisible":null,"nav":[{"createdAt":"2022-11-11T12:07:30.576Z","title":"国内大厂","icon":null,"ownVisible":null,"nav":[{"name":"阿里云","createdAt":"2022-11-11T12:13:28.753Z","rate":5,"desc":"国内服务器一哥","top":false,"ownVisible":false,"icon":"https://img.alicdn.com/tfs/TB1ugg7M9zqK1RjSZPxXXc4tVXa-32-32.png_.webp","url":"https://www.alibabacloud.com/","urls":{}},{"name":"腾讯云","createdAt":"2022-11-11T12:10:30.487Z","rate":5,"desc":"国内服务器二哥","top":false,"ownVisible":false,"icon":"https://cloud.tencent.com/favicon.ico","url":"https://cloud.tencent.com/","urls":{}},{"name":"华为云","createdAt":"2022-11-11T12:17:40.910Z","rate":4,"desc":"实力也可以的","top":false,"ownVisible":false,"icon":"https://res-static.hc-cdn.cn/aem/content/dam/cloudbu-site/archive/commons/web_resoure/cms/static/images/global/favicon.ico?sttl=1.0.5","url":"https://www.huaweicloud.com/","urls":{}},{"name":"京东云","createdAt":"2022-11-11T12:22:41.865Z","rate":5,"desc":"京东旗下","top":false,"ownVisible":false,"icon":"https://img1.jcloudcs.com/portal/jdy-touch-icon.png","url":"https://www.jdcloud.com/","urls":{}},{"name":"天翼云","createdAt":"2022-11-11T12:21:12.953Z","rate":4,"desc":"中国电信旗下","top":false,"ownVisible":false,"icon":"https://www.ctyun.cn/favicon.ico","url":"https://www.ctyun.cn/","urls":{}},{"name":"百度云","createdAt":"2022-11-11T12:15:44.938Z","rate":4,"desc":"存在感没阿里腾讯强","top":false,"ownVisible":false,"icon":"https://bce.bdstatic.com/img/favicon.ico","url":"https://cloud.baidu.com/","urls":{}}]},{"createdAt":"2022-11-13T05:08:14.911Z","title":"国内二线","icon":null,"ownVisible":null,"nav":[{"name":"西部数码","createdAt":"2022-11-13T05:09:27.646Z","rate":4.5,"desc":"老牌云计算服务商,域名后缀很多","top":false,"ownVisible":false,"icon":"https://www.west.cn/favicon.png","url":"https://www.west.cn/","urls":{}},{"name":"尊云","createdAt":"2022-11-13T05:18:24.898Z","rate":4,"desc":"域名应该挺值钱","top":false,"ownVisible":false,"icon":"http://www.zun.com/favicon.ico","url":"http://www.zun.com/","urls":{}},{"name":"小鸟云","createdAt":"2022-11-13T05:15:24.531Z","rate":4.5,"desc":"名字我挺喜欢的","top":false,"ownVisible":false,"icon":"https://www.niaoyun.com/favicon.ico","url":"https://www.niaoyun.com/","urls":{}},{"name":"硅云","createdAt":"2022-11-13T10:30:45.861Z","rate":4,"desc":"主要做香港服务器","top":false,"ownVisible":false,"icon":"https://cdn.vpsor.cn/favicon.ico?v=202103251312","url":"https://www.vpsor.cn/","urls":{}},{"name":"景安网络","createdAt":"2022-11-13T05:11:18.753Z","rate":4,"desc":"腾讯云河南授权销售中心","top":false,"ownVisible":false,"icon":"https://www.zzidc.com/favicon.ico","url":"https://www.zzidc.com/","urls":{}},{"name":"快云","createdAt":"2022-11-13T05:17:21.639Z","rate":4,"desc":"好像和苹果CMS有关系","top":false,"ownVisible":false,"icon":"https://www.kuaiyun.cn/favicon.ico","url":"https://www.kuaiyun.cn/","urls":{}}]},{"createdAt":"2022-11-13T10:24:06.760Z","title":"国外厂商","icon":null,"ownVisible":null,"nav":[{"name":"Vultr","createdAt":"2022-11-14T11:46:44.363Z","rate":5,"desc":"国内知名度很高,支持支付宝","top":false,"ownVisible":false,"icon":"https://www.vultr.com/favicon.ico","url":"https://www.vultr.com/","urls":{}},{"name":"Hostwinds","createdAt":"2022-11-14T11:45:12.266Z","rate":4,"desc":"主要经营美国vps,支持支付宝","top":false,"ownVisible":false,"icon":"https://www.hostwinds.com/favicon.ico","url":"https://www.hostwinds.com/","urls":{}},{"name":"亚马逊云服务","createdAt":"2022-11-13T10:28:49.705Z","rate":4,"desc":"注册享12个月免费用","top":false,"ownVisible":false,"icon":"https://aws.amazon.com/favicon.ico","url":"https://aws.amazon.com/cn/","urls":{}},{"name":"RAKSmart","createdAt":"2022-11-13T10:42:23.058Z","rate":4,"desc":"美国华人创办","top":false,"ownVisible":false,"icon":"https://www.raksmart.com/static/images/logo3.png","url":"https://www.raksmart.com/","urls":{}},{"name":"Bluehost","createdAt":"2022-11-13T10:40:13.954Z","rate":4,"desc":"虚拟主机比较出名","top":false,"ownVisible":false,"icon":"https://cn.bluehost.com/ui/resellerdata/510000_539999/511678/supersite2/bluehost/themes/MinimalGreen-MyTheme/images/myUploadedImages/favicon.ico","url":"https://cn.bluehost.com/","urls":{}}]},{"createdAt":"2022-11-13T10:24:23.420Z","title":"小众厂商","icon":"","ownVisible":null,"nav":[{"name":"老薛主机","createdAt":"2022-11-14T11:50:22.855Z","rate":5,"desc":"香港主机比较出名,服务很好,我第一次建网站就是用的他家的主机","top":false,"ownVisible":false,"icon":"https://www.laoxuehost.com/favicon.ico","url":"https://www.laoxuehost.com/","urls":{}},{"name":"彩虹云主机","createdAt":"2022-11-14T11:54:19.792Z","rate":4.5,"desc":"一个大佬的","top":false,"ownVisible":false,"icon":"https://www.cccyun.net/favicon.ico","url":"https://www.cccyun.net/","urls":{}},{"name":"小白云","createdAt":"2022-11-14T11:56:25.391Z","rate":4,"desc":"和彩虹应该也是一伙的","top":false,"ownVisible":false,"icon":"https://www.xiaobaiyun.cn/favicon.ico","url":"https://www.xiaobaiyun.cn/","urls":{}},{"name":"融兴云机","createdAt":"2022-11-14T12:12:05.063Z","rate":4,"desc":"融兴解析旗下,支持国内无备案","top":false,"ownVisible":false,"icon":"https://www.rxyunji.com/favicon.ico","url":"https://www.rxyunji.com/","urls":{}},{"name":"乐数云","createdAt":"2022-11-14T12:00:00.693Z","rate":4,"desc":"有免费主机,可以测试源码","top":false,"ownVisible":false,"icon":"","url":"https://leshuyun.com/","urls":{}},{"name":"狗云","createdAt":"2022-11-14T12:07:44.653Z","rate":4,"desc":"搜集自浩瀚的网络","top":false,"ownVisible":false,"icon":"https://assets.dogyun.com/home/img/logo-128px.png","url":"https://www.dogyun.com/","urls":{}},{"name":"触摸云","createdAt":"2022-11-14T12:05:39.195Z","rate":4,"desc":"搜集自浩瀚的网络","top":false,"ownVisible":false,"icon":"https://cmzi.com/themes/web/ostin/assets/img/favicon.png","url":"https://cmzi.com/","urls":{}},{"name":"无限大云","createdAt":"2022-11-14T12:02:54.410Z","rate":4,"desc":"麒麟采集站旗下","top":false,"ownVisible":false,"icon":null,"url":"https://www.wuxiandayun.com/","urls":{}},{"name":"谷信云","createdAt":"2022-11-15T11:51:18.897Z","rate":4,"desc":"搜集自浩瀚的网络","top":false,"ownVisible":false,"icon":"https://www.iudun.com/favicon.ico","url":"https://www.iudun.com/","urls":{}}]}]},{"createdAt":"2022-11-08T01:56:48.271Z","title":"域名/CDN","icon":null,"ownVisible":null,"nav":[{"createdAt":"2022-11-14T12:17:26.443Z","title":"域名注册","icon":null,"ownVisible":null,"nav":[{"name":"阿里云万网","createdAt":"2022-11-14T12:25:54.458Z","rate":5,"desc":"阿里云旗下","top":false,"ownVisible":false,"icon":"https://img.alicdn.com/tfs/TB1_ZXuNcfpK1RjSZFOXXa6nFXa-32-32.ico","url":"https://wanwang.aliyun.com/","urls":{}},{"name":"腾讯DNSPod","createdAt":"2022-11-14T12:23:55.118Z","rate":4.5,"desc":"腾讯云旗下","top":false,"ownVisible":false,"icon":"https://www.dnspod.cn/favicon.ico","url":"https://www.dnspod.cn/","urls":{}},{"name":"GoDaddy","createdAt":"2022-11-14T12:43:59.606Z","rate":4.5,"desc":"狗爹,管理全球8200+万域名","top":false,"ownVisible":false,"icon":"","url":"http://www.godaddy.com/","urls":{}},{"name":"Name","createdAt":"2022-11-14T12:42:06.573Z","rate":4.5,"desc":"国际知名老牌注册商","top":false,"ownVisible":false,"icon":"https://www.name.com/favicon.ico","url":"https://www.name.com/","urls":{}},{"name":"新网","createdAt":"2022-11-15T11:19:31.171Z","rate":4,"desc":"国内域名注册商","top":false,"ownVisible":false,"icon":"https://www.xinnet.com/favicon.ico","url":"https://www.xinnet.com/","urls":{}},{"name":"Domain","createdAt":"2022-11-14T12:32:47.086Z","rate":4.5,"desc":"国外知名注册商","top":false,"ownVisible":false,"icon":"https://www.domain.com/favicon.ico","url":"https://www.domain.com/","urls":{}},{"name":"101domain","createdAt":"2022-11-14T12:38:20.988Z","rate":4,"desc":"国外老牌域名注册服务商,后缀挺多","top":false,"ownVisible":false,"icon":"https://www.101domain.com/images/101domain/favicon/favicon-32x32.png?20221109052028","url":"https://www.101domain.com/","urls":{}},{"name":"中资源","createdAt":"2022-11-15T00:04:14.281Z","rate":4,"desc":"国内新后缀注册商","top":false,"ownVisible":false,"icon":"https://www.zzy.cn/images/favicon32.ico","url":"https://www.zzy.com","urls":{}},{"name":"趣域网","createdAt":"2022-11-15T00:05:28.662Z","rate":4,"desc":"国内非主流后缀注册商","top":false,"ownVisible":false,"icon":"https://www.quyu.net/favicon.ico","url":"https://www.quyu.net/","urls":{}},{"name":"Namecheap","createdAt":"2022-11-14T12:36:22.431Z","rate":4.5,"desc":"国际优秀服务域名注册商","top":false,"ownVisible":false,"icon":"https://www.namecheap.com/favicon.ico","url":"https://www.namecheap.com/","urls":{}},{"name":"Gandi","createdAt":"2022-11-14T12:40:17.505Z","rate":4.5,"desc":"750种顶级域名,支持中文,价格稍高","top":false,"ownVisible":false,"icon":"https://www.gandi.net/favicon.ico","url":"https://www.gandi.net/","urls":{}},{"name":"Uniregistry","createdAt":"2022-11-14T12:35:04.255Z","rate":4.5,"desc":"GoDaddy旗下批量查询注册","top":false,"ownVisible":false,"icon":"https://uniregistry.com/favicon.ico","url":"https://uniregistry.com/","urls":{}}]},{"createdAt":"2022-11-14T12:17:34.911Z","title":"域名交易","icon":null,"ownVisible":null,"nav":[{"name":"万网域名交易","createdAt":"2022-11-14T12:47:21.311Z","rate":4.5,"desc":"略","top":false,"ownVisible":false,"icon":"https://img.alicdn.com/tfs/TB1_ZXuNcfpK1RjSZFOXXa6nFXa-32-32.ico","url":"https://mi.aliyun.com/","urls":{}},{"name":"Dan","createdAt":"2022-11-14T12:52:34.693Z","rate":5,"desc":"简单而又认真的域名交易平台","top":false,"ownVisible":false,"icon":"https://cdn3.dan.com/assets/icons/favicon-17cae8213bf0fbeae27b644f0616b74981f348af943f27b73abf8e7b3a557b8f.ico","url":"https://dan.com/","urls":{}},{"name":"聚名网","createdAt":"2022-11-15T00:11:23.558Z","rate":4.5,"desc":"国内域名抢注,交易平台","top":false,"ownVisible":false,"icon":"https://www.juming.com/pub/img/juming_ico.ico","url":"https://www.juming.com/","urls":{}},{"name":"Sedo","createdAt":"2022-11-14T12:51:23.650Z","rate":4.5,"desc":"全球最大的域名交易平台","top":false,"ownVisible":false,"icon":"https://sedo.com/favicon.ico","url":"https://sedo.com/","urls":{}},{"name":"3H Dmains","createdAt":"2022-11-14T12:55:44.894Z","rate":4,"desc":"正努力成为国内领先的域名交易平台","top":false,"ownVisible":false,"icon":null,"url":"https://www.hhh.org/","urls":{}},{"name":"易名网","createdAt":"2022-11-14T12:50:01.181Z","rate":4,"desc":"国内域名交易平台","top":false,"ownVisible":false,"icon":"https://www.ename.com/favicon.ico","url":"https://www.ename.com/","urls":{}},{"name":"爱名网","createdAt":"2022-11-14T12:48:45.750Z","rate":4,"desc":"域名卖卖,域名拍卖","top":false,"ownVisible":false,"icon":"https://www.22.cn/favicon.ico","url":"https://www.22.cn/","urls":{}}]},{"createdAt":"2022-11-14T12:20:41.452Z","title":"CDN","icon":null,"ownVisible":null,"nav":[{"name":"CloudFlare","createdAt":"2022-11-15T11:25:38.999Z","rate":5,"desc":"全球免费CDN龙头","top":false,"ownVisible":false,"icon":"https://www.cloudflare.com/favicon.ico","url":"https://www.cloudflare.com/","urls":{}},{"name":"又拍云","createdAt":"2022-11-15T11:36:43.986Z","rate":5,"desc":"主要提供云存储和CDN加速服务,国内比较推荐","top":false,"ownVisible":false,"icon":"https://www.upyun.com/favicon.ico","url":"https://www.upyun.com/","urls":{}},{"name":"百度CDN","createdAt":"2022-11-15T11:28:20.661Z","rate":5,"desc":"百度就CDN还算良心","top":false,"ownVisible":false,"icon":"https://yjsstatic.su.baidu.com/app/favicon.ico","url":"https://su.baidu.com/","urls":{}},{"name":"七牛云","createdAt":"2022-11-15T11:35:41.021Z","rate":4.5,"desc":"和又拍云一样","top":false,"ownVisible":false,"icon":"https://www.qiniu.com/favicon.ico","url":"https://www.qiniu.com/","urls":{}},{"name":"帝恩思","createdAt":"2022-11-15T11:44:10.577Z","rate":4.5,"desc":"DNS.COM,提供高仿DNS","top":false,"ownVisible":false,"icon":"https://www.dns.com/favicon.ico","url":"https://www.dns.com/","urls":{}},{"name":"奇安信网站卫士","createdAt":"2022-11-15T11:39:38.053Z","rate":4,"desc":"360旗下,宣称将免费进行到底","top":false,"ownVisible":false,"icon":null,"url":"https://wangzhan.qianxin.com/","urls":{}},{"name":"恰啦","createdAt":"2022-11-15T11:48:34.280Z","rate":4,"desc":"高防CDN,搜集自浩瀚的网络","top":false,"ownVisible":false,"icon":null,"url":"https://qia.la/","urls":{}},{"name":"防护啦","createdAt":"2022-11-15T11:47:03.747Z","rate":4,"desc":"高防CDN,搜集自浩瀚的网络","top":false,"ownVisible":false,"icon":"","url":"http://waf.la/","urls":{}},{"name":"天御云","createdAt":"2022-11-16T11:01:17.129Z","rate":4.5,"desc":"搜集自浩瀚的网络","top":false,"ownVisible":false,"icon":"https://tyucdn.com/favicon.ico","url":"https://tyucdn.com/","urls":{}}]}]},{"createdAt":"2022-11-08T01:56:23.645Z","title":"建站程序","icon":null,"ownVisible":null,"nav":[{"createdAt":"2022-11-15T11:52:01.100Z","title":"博客","icon":null,"ownVisible":null,"nav":[{"name":"WordPress","createdAt":"2022-11-15T11:57:50.348Z","rate":5,"desc":"功能十分强大","top":false,"ownVisible":false,"icon":"https://cn.wordpress.org/favicon.ico","url":"https://cn.wordpress.org/","urls":{}},{"name":"Typecho","createdAt":"2022-11-15T11:59:07.259Z","rate":5,"desc":"一款轻量级博客程序","top":false,"ownVisible":false,"icon":"http://typecho.org/favicon.ico","url":"http://typecho.org/","urls":{}},{"name":"ZBlog","createdAt":"2022-11-15T12:00:12.901Z","rate":5,"desc":"一款优秀的国内开源博客程序","top":false,"ownVisible":false,"icon":"https://www.zblogcn.com/favicon.ico","url":"https://www.zblogcn.com/","urls":{}},{"name":"Hexo","createdAt":"2022-11-15T12:01:06.302Z","rate":4,"desc":"一款纯静态博客程序","top":false,"ownVisible":false,"icon":"https://hexo.io/favicon.ico","url":"https://hexo.io/","urls":{}},{"name":"Halo","createdAt":"2022-11-18T13:20:46.820Z","rate":4.5,"desc":"一款优秀的JAVA开源博客程序","top":false,"ownVisible":false,"icon":"https://halo.run/favicon.ico","url":"https://halo.run/","urls":{}},{"name":"Gridea","createdAt":"2022-11-18T13:22:01.249Z","rate":4.5,"desc":"一个静态博客写作客户端","top":false,"ownVisible":false,"icon":"https://gridea.dev/favicon.ico","url":"https://gridea.dev/","urls":{}}]},{"createdAt":"2022-11-15T11:53:23.294Z","title":"影视CMS","icon":null,"ownVisible":null,"nav":[{"name":"苹果CMS","createdAt":"2022-11-15T12:07:56.558Z","rate":5,"desc":"简单好使的影视CMS","top":false,"ownVisible":false,"icon":"https://github.com/favicon.ico","url":"https://github.com/magicblack","urls":{}},{"name":"海洋CMS","createdAt":"2022-11-15T12:12:08.885Z","rate":4,"desc":"简单,快速,稳定,开源","top":false,"ownVisible":false,"icon":"https://seacms.net/favicon.ico","url":"https://seacms.net/","urls":{}},{"name":"飞飞CMS","createdAt":"2022-11-15T12:10:51.954Z","rate":4,"desc":"一款免费开源的PHP电影程序","top":false,"ownVisible":false,"icon":null,"url":"https://www.feifeicms.org/","urls":{}},{"name":"魅思CMS","createdAt":"2022-11-15T12:18:04.750Z","rate":4,"desc":"收费CMS","top":false,"ownVisible":false,"icon":"http://www.msvod.cc/favicon.ico","url":"http://www.msvod.cc/","urls":{}},{"name":"赞片CMS","createdAt":"2022-11-15T12:16:50.126Z","rate":4,"desc":"收费CMS","top":false,"ownVisible":false,"icon":null,"url":"https://zanpiancms.com/","urls":{}},{"name":"赤兔CMS","createdAt":"2022-11-15T12:13:31.992Z","rate":4,"desc":"宣称已成为全球影视站长首选","top":false,"ownVisible":false,"icon":null,"url":"http://ctcms.cn/","urls":{}}]},{"createdAt":"2022-11-15T11:54:14.465Z","title":"论坛","icon":null,"ownVisible":null,"nav":[{"name":"Discuz","createdAt":"2022-11-15T12:19:47.960Z","rate":5,"desc":"免费开源PHP论坛程序","top":false,"ownVisible":false,"icon":"https://discuz.dismall.com/favicon.ico","url":"https://discuz.dismall.com/","urls":{}},{"name":"Xiuno","createdAt":"2022-11-15T12:23:18.101Z","rate":5,"desc":"新兴开源论坛程序","top":false,"ownVisible":false,"icon":"https://xiunobbs.cn/favicon.ico","url":"https://xiunobbs.cn/","urls":{}}]},{"createdAt":"2022-11-15T11:54:36.009Z","title":"淘客CMS","icon":null,"ownVisible":null,"nav":[{"name":"好单库CMS","createdAt":"2022-11-15T12:26:07.900Z","rate":5,"desc":"目前建议淘客CMS","top":false,"ownVisible":false,"icon":"https://www.haodanku.com/favicon.ico","url":"https://www.haodanku.com/cms/intro","urls":{}},{"name":"大淘客CMS","createdAt":"2022-11-15T12:27:31.421Z","rate":5,"desc":"目前建议淘客CMS","top":false,"ownVisible":false,"icon":"http://cms.dataoke.com/favicon.ico","url":"http://cms.dataoke.com/","urls":{}},{"name":"好淘客CMS","createdAt":"2022-11-15T12:32:52.568Z","rate":4,"desc":"不止淘客CMS","top":false,"ownVisible":false,"icon":"http://www.haotaoke.cn/favicon.ico","url":"http://www.haotaoke.cn/","urls":{}},{"name":"推卷客","createdAt":"2022-11-15T12:34:09.573Z","rate":4,"desc":"免费/付费都有","top":false,"ownVisible":false,"icon":"https://www.tuiquanke.com/favicon.ico","url":"https://www.tuiquanke.com/","urls":{}},{"name":"飞飞侠淘客CMS","createdAt":"2022-11-15T12:29:58.811Z","rate":4,"desc":"付费CMS","top":false,"ownVisible":false,"icon":"https://bb.ffxia.cn/favicon.ico","url":"https://bb.ffxia.cn/","urls":{}}]},{"createdAt":"2022-11-15T11:54:58.157Z","title":"其他","icon":null,"ownVisible":null,"nav":[{"name":"Alist","createdAt":"2022-11-18T13:18:25.501Z","rate":5,"desc":"一个非常好用的开源在线网盘程序","top":false,"ownVisible":false,"icon":"https://github.com/favicon.ico","url":"https://github.com/alist-org/alist","urls":{}},{"name":"简单图床","createdAt":"2022-11-18T12:00:27.852Z","rate":5,"desc":"自用款,简洁好使","top":false,"ownVisible":false,"icon":"https://github.com/favicon.ico","url":"https://github.com/icret/EasyImages2.0","urls":{}},{"name":"兰空图床","createdAt":"2022-11-18T11:59:18.598Z","rate":5,"desc":"一款优秀的开源图床程序","top":false,"ownVisible":false,"icon":"https://github.com/favicon.ico","url":"https://github.com/lsky-org/lsky-pro","urls":{}},{"name":"织梦CMS","createdAt":"2022-11-15T12:35:37.212Z","rate":4.5,"desc":"老牌内容管理系统","top":false,"ownVisible":false,"icon":"https://www.dedecms.com/assets/favicon.ico","url":"https://www.dedecms.com/","urls":{}},{"name":"智简魔方","createdAt":"2022-11-16T12:42:17.825Z","rate":4.5,"desc":"服务器管理销售系统","top":false,"ownVisible":false,"icon":null,"url":"https://www.idcsmart.com/","urls":{}},{"name":"帝国CMS","createdAt":"2022-11-15T12:39:15.627Z","rate":4,"desc":"和织梦CMS一样","top":false,"ownVisible":false,"icon":"","url":"http://www.phome.net/","urls":{}},{"name":"友价源码","createdAt":"2022-11-15T12:40:48.355Z","rate":4,"desc":"友价商城比较出名","top":false,"ownVisible":false,"icon":null,"url":"https://www.yj99.cn/","urls":{}},{"name":"ECshop","createdAt":"2022-11-15T12:45:22.084Z","rate":4,"desc":"商城系统","top":false,"ownVisible":false,"icon":"https://www.ecshop.com/favicon.ico","url":"https://www.ecshop.com/","urls":{}}]}]},{"createdAt":"2022-11-08T01:56:59.639Z","title":"常用工具","icon":null,"ownVisible":null,"nav":[{"createdAt":"2022-11-16T11:05:09.728Z","title":"综合工具","icon":"","ownVisible":null,"nav":[{"name":"Ping.cn","createdAt":"2022-11-18T13:51:51.843Z","rate":4.5,"desc":"网站测速,简洁无广","top":false,"ownVisible":false,"icon":"https://ping.cn/favicon.ico","url":"https://ping.cn/","urls":{}},{"name":"宝塔","createdAt":"2022-11-16T11:24:33.221Z","rate":5,"desc":"国内用户量最多的免费服务器管理面板","top":false,"ownVisible":false,"icon":"https://www.bt.cn/favicon.ico","url":"https://www.bt.cn/","urls":{}},{"name":"站长工具","createdAt":"2022-11-16T11:20:14.833Z","rate":5,"desc":"站长之家旗下,功能全,广告多","top":false,"ownVisible":false,"icon":"https://tool.chinaz.com/favicon.ico","url":"https://tool.chinaz.com/","urls":{}},{"name":"爱站网工具","createdAt":"2022-11-16T11:22:27.632Z","rate":5,"desc":"和站长之家工具形成国内站长工具两巨头","top":false,"ownVisible":false,"icon":"https://www.aizhan.com/favicon.ico","url":"https://www.aizhan.com/","urls":{}},{"name":"拨测","createdAt":"2022-11-16T11:36:37.907Z","rate":4.5,"desc":"新兴综合查询平台,主要提供网站测速","top":false,"ownVisible":false,"icon":"https://www.boce.com/favicon.ico","url":"https://www.boce.com/","urls":{}}]},{"createdAt":"2022-11-16T11:06:08.695Z","title":"网站统计","icon":null,"ownVisible":null,"nav":[{"name":"51LA","createdAt":"2022-11-16T11:43:55.030Z","rate":5,"desc":"个人比较喜欢的个性统计平台","top":false,"ownVisible":false,"icon":"https://www.51.la/favicon.ico","url":"https://www.51.la/","urls":{}},{"name":"百度统计","createdAt":"2022-11-16T11:39:15.105Z","rate":4.5,"desc":"这个没啥说的","top":false,"ownVisible":false,"icon":"http://tm.baidu.com/favicon.ico","url":"http://tm.baidu.com/","urls":{}},{"name":"友盟+","createdAt":"2022-11-16T11:42:49.212Z","rate":4.5,"desc":"CNZZ和友盟合并成立友盟+","top":false,"ownVisible":false,"icon":"https://www.umeng.com/favicon.ico","url":"https://www.umeng.com/","urls":{}},{"name":"谷歌统计","createdAt":"2022-11-16T11:47:56.763Z","rate":4,"desc":"有人喜欢用老外的","top":false,"ownVisible":false,"icon":null,"url":"https://analytics.google.com/","urls":{}}]},{"createdAt":"2022-11-18T11:37:46.588Z","title":"图床","icon":null,"ownVisible":null,"nav":[{"name":"路过图床","createdAt":"2022-11-18T11:46:56.512Z","rate":4.5,"desc":"国内免费图床","top":false,"ownVisible":false,"icon":"https://imgse.com/content/images/system/favicon_1587118523486_91617a.png","url":"https://imgse.com/","urls":{}},{"name":"图林","createdAt":"2022-11-18T11:57:30.927Z","rate":4.5,"desc":"国内免费图床","top":false,"ownVisible":false,"icon":null,"url":"https://imglink.org/","urls":{}},{"name":"图仓","createdAt":"2022-11-18T11:55:29.995Z","rate":4.5,"desc":"国内免费图床","top":false,"ownVisible":false,"icon":null,"url":"https://www.imagehub.cc/","urls":{}},{"name":"Z4A图床","createdAt":"2022-11-18T11:53:56.202Z","rate":4.5,"desc":"要做国内最良心的图床","top":false,"ownVisible":false,"icon":"https://www.z4a.net/favicon.ico","url":"https://www.z4a.net/","urls":{}},{"name":"SM.MS","createdAt":"2022-11-18T11:53:02.338Z","rate":4.5,"desc":"国外知名图床","top":false,"ownVisible":false,"icon":"https://sm.ms/favicon.ico","url":"https://sm.ms/","urls":{}},{"name":"聚合图床","createdAt":"2022-11-18T11:51:23.215Z","rate":5,"desc":"国内收费图床","top":false,"ownVisible":false,"icon":"https://www.superbed.cn/favicon.ico","url":"https://www.superbed.cn/","urls":{}},{"name":"TG图床","createdAt":"2022-11-18T11:50:03.510Z","rate":5,"desc":"国内免费图床","top":false,"ownVisible":false,"icon":"","url":"https://imgtg.com/","urls":{}}]},{"createdAt":"2022-11-16T11:08:25.671Z","title":"网站安全","icon":null,"ownVisible":null,"nav":[{"name":"安全狗","createdAt":"2022-11-16T11:56:12.204Z","rate":4.5,"desc":"一站式云计算安全平台","top":false,"ownVisible":false,"icon":"https://www.safedog.cn/favicon.ico","url":"https://www.safedog.cn/","urls":{}},{"name":"护卫神","createdAt":"2022-11-16T12:02:22.929Z","rate":4.5,"desc":"服务器安全防护","top":false,"ownVisible":false,"icon":"https://www.hws.com/favicon.ico","url":"https://www.hws.com/","urls":{}},{"name":"知道创宇","createdAt":"2022-11-16T11:58:17.979Z","rate":4.5,"desc":"看人家域名就知道干啥的","top":false,"ownVisible":false,"icon":null,"url":"https://www.yunaq.com/","urls":{}},{"name":"GOODWAF","createdAt":"2022-11-16T12:04:19.961Z","rate":4,"desc":"终身免费WEB应用防火墙","top":false,"ownVisible":false,"icon":"http://goodwaf.cn/favicon.ico","url":"http://goodwaf.cn/","urls":{}}]},{"createdAt":"2022-11-16T11:08:34.798Z","title":"网站推广","icon":null,"ownVisible":null,"nav":[{"name":"百度收录","createdAt":"2022-11-16T12:08:00.487Z","rate":5,"desc":"不得不说百度是个好公司（快收录）","top":false,"ownVisible":false,"icon":"https://ziyuan.baidu.com/favicon.ico","url":"https://ziyuan.baidu.com/dailysubmit/index","urls":{}},{"name":"必应收录","createdAt":"2022-11-16T12:15:11.850Z","rate":5,"desc":"多多益善","top":false,"ownVisible":false,"icon":"http://www.bing.com/favicon.ico","url":"http://www.bing.com/toolbox/submit-site-url","urls":{}},{"name":"谷歌收录","createdAt":"2022-11-16T12:19:08.178Z","rate":4.5,"desc":"多多益善","top":false,"ownVisible":false,"icon":"","url":"http://www.google.cn/intl/zh-CN/add_url.html","urls":{}},{"name":"360收录","createdAt":"2022-11-16T12:12:43.216Z","rate":5,"desc":"多多益善","top":false,"ownVisible":false,"icon":"http://zhanzhang.so.com/favicon.ico","url":"http://zhanzhang.so.com/?m=PageInclude&a=index","urls":{}},{"name":"搜狗收录","createdAt":"2022-11-16T12:12:09.841Z","rate":5,"desc":"收录多多益善","top":false,"ownVisible":false,"icon":"https://dlweb.sogoucdn.com/translate/favicon.ico?v=20180424","url":"http://zhanzhang.sogou.com/index.php/urlSubmit/index","urls":{}},{"name":"360信用认证","createdAt":"2022-11-16T12:23:00.020Z","rate":4,"desc":"有信用更放心","top":false,"ownVisible":false,"icon":"https://xinyong.360.cn/favicon.ico","url":"https://xinyong.360.cn/","urls":{}},{"name":"孙悟空收录","createdAt":"2022-11-16T12:20:29.887Z","rate":4,"desc":"多多益善","top":false,"ownVisible":false,"icon":"http://www.swkong.com/favicon.ico","url":"http://www.swkong.com/add.php","urls":{}}]}]},{"createdAt":"2022-11-15T12:46:10.492Z","title":"论坛/博客","icon":null,"ownVisible":null,"nav":[{"createdAt":"2022-11-16T12:26:50.117Z","title":"论坛","icon":null,"ownVisible":null,"nav":[{"name":"4414论坛","createdAt":"2022-11-16T12:29:39.896Z","rate":5,"desc":"目前还比较活跃的一个站长论坛","top":false,"ownVisible":false,"icon":"https://www.4414.cn/favicon.ico","url":"https://www.4414.cn/","urls":{}},{"name":"十年之约","createdAt":"2022-11-16T12:31:08.623Z","rate":5,"desc":"博客“十年之约”活动官方论坛","top":false,"ownVisible":false,"icon":"https://xyears.cn/view/img/favicon.ico","url":"https://xyears.cn/","urls":{}},{"name":"站长窝","createdAt":"2022-11-16T12:36:39.784Z","rate":4.5,"desc":"主要讨论苹果CMS","top":false,"ownVisible":false,"icon":null,"url":"https://bbs.zhanzhangwo.com/","urls":{}},{"name":"非主流论坛","createdAt":"2022-11-16T12:35:16.754Z","rate":5,"desc":"主要讨论非主流后缀域名,还比较活跃","top":false,"ownVisible":false,"icon":"","url":"https://loc.cc/","urls":{}},{"name":"Xiuno交流论坛","createdAt":"2022-11-16T12:33:16.143Z","rate":5,"desc":"不知道是不是官方","top":false,"ownVisible":false,"icon":"https://xiunobbs.cn/favicon.ico","url":"https://xiunobbs.cn/","urls":{}}]},{"createdAt":"2022-11-16T12:27:21.918Z","title":"博客","icon":null,"ownVisible":null,"nav":[{"name":"友人m的笔记","createdAt":"2022-11-16T12:38:38.092Z","rate":5,"desc":"是友人,不是m","top":false,"ownVisible":false,"icon":null,"url":"https://blog.hao502.com","urls":{}},{"name":"云游君的小站","createdAt":"2022-11-18T13:07:51.378Z","rate":4.5,"desc":"云游君,代表作品：便携小空调","top":false,"ownVisible":false,"icon":"https://yunyoujun.cn/favicon.svg","url":"https://yunyoujun.cn/","urls":{}},{"name":"缤纷彩虹天地","createdAt":"2022-11-18T13:09:29.166Z","rate":4.5,"desc":"彩虹,代表作品：彩虹云任务等...","top":false,"ownVisible":false,"icon":"https://blog.cccyun.cn/favicon.ico","url":"https://blog.cccyun.cn/","urls":{}},{"name":"AE博客","createdAt":"2022-11-18T13:11:44.637Z","rate":4.5,"desc":"墨渊,代表作品：优启梦域名防洪","top":false,"ownVisible":false,"icon":"http://www.aeink.com/favicon.ico","url":"http://www.aeink.com/","urls":{}},{"name":"樗顾","createdAt":"2022-11-18T13:26:56.325Z","rate":4.5,"desc":"山卜方,代表作品：Typecho主题Pigeon","top":false,"ownVisible":false,"icon":"https://novcu.com/logo.png","url":"https://novcu.com/","urls":{}}]}]},{"createdAt":"2022-11-16T11:12:56.065Z","title":"其他","icon":null,"ownVisible":null,"nav":[{"createdAt":"2022-11-18T12:16:58.554Z","title":"短网址/防洪","icon":null,"ownVisible":null,"nav":[{"name":"QQ微信防洪","createdAt":"2022-11-18T12:54:50.217Z","rate":5,"desc":"目标很明确","top":false,"ownVisible":false,"icon":null,"url":"http://qqwxfh.com/","urls":{}},{"name":"91She防洪","createdAt":"2022-11-18T12:52:07.036Z","rate":5,"desc":"看样子又和彩虹有关系","top":false,"ownVisible":false,"icon":"https://www.91she.cn/favicon.ico","url":"https://www.91she.cn/","urls":{}},{"name":"UC短网址","createdAt":"2022-11-18T12:48:09.649Z","rate":4.5,"desc":"专业域名缩短抗封服务","top":false,"ownVisible":false,"icon":"https://www.uc4.cn/favicon.ico","url":"https://www.uc4.cn/","urls":{}},{"name":"六度短网址","createdAt":"2022-11-18T12:47:23.894Z","rate":5,"desc":"带统计的,有付费服务","top":false,"ownVisible":false,"icon":null,"url":"https://6du.in/","urls":{}},{"name":"C1N短网址","createdAt":"2022-11-18T12:43:06.935Z","rate":5,"desc":"免费短网址平台","top":false,"ownVisible":false,"icon":"https://www.c1n.cn/img/logo.png","url":"https://www.c1n.cn/","urls":{}},{"name":"短网址","createdAt":"2022-11-18T12:39:51.956Z","rate":5,"desc":"人家名字就叫短网址","top":false,"ownVisible":false,"icon":"https://www.dwz.lc/favicon.ico","url":"https://www.dwz.lc/","urls":{}}]},{"createdAt":"2022-11-18T12:17:27.286Z","title":"主题模板","icon":null,"ownVisible":null,"nav":[{"name":"Typecho南博主题","createdAt":"2022-11-18T13:36:46.386Z","rate":4.5,"desc":"小众朋友圈风格,缺点细节做的不好,也没有后续更新了","top":false,"ownVisible":false,"icon":"https://github.com/favicon.ico","url":"https://github.com/krait-team/Nabo-theme-typecho","urls":{}},{"name":"Hexo主题yun","createdAt":"2022-11-18T13:33:45.326Z","rate":4.5,"desc":"云游君同款","top":false,"ownVisible":false,"icon":"https://github.com/favicon.ico","url":"https://github.com/YunYouJun/hexo-theme-yun/","urls":{}},{"name":"子比主题","createdAt":"2022-11-18T13:28:40.006Z","rate":4.5,"desc":"一款强大的WodPress主题","top":false,"ownVisible":false,"icon":"https://oss.zibll.com/zibll.com/2020/03/favicon-1.png","url":"https://www.zibll.com/","urls":{}},{"name":"日主题","createdAt":"2022-11-18T12:37:37.787Z","rate":4.5,"desc":"一款比较火的WordPress资源下载主题","top":false,"ownVisible":false,"icon":"https://ritheme.com/wp-content/uploads/2021/09/faviconicon.png","url":"https://ritheme.com/","urls":{}}]},{"createdAt":"2022-11-18T12:17:17.918Z","title":"源码资源","icon":null,"ownVisible":null,"nav":[{"name":"源分享","createdAt":"2022-11-18T13:48:45.062Z","rate":4.5,"desc":"多款原创程序,代表产品源支付","top":false,"ownVisible":false,"icon":"https://www.yfx.top/wp-content/uploads/2021/02/1613648623-d02a42d9cb3dec9.png","url":"https://www.yfx.top/","urls":{}},{"name":"二层楼源码","createdAt":"2022-11-18T13:45:36.366Z","rate":4.5,"desc":"搜集自浩瀚的网络","top":false,"ownVisible":false,"icon":"","url":"https://www.rclou.cn/","urls":{}},{"name":"互站网","createdAt":"2022-11-18T13:43:58.096Z","rate":4.5,"desc":"国内知名的源码交易中心","top":false,"ownVisible":false,"icon":"https://www.huzhan.com/favicon.ico","url":"https://www.huzhan.com/","urls":{}}]},{"createdAt":"2022-11-18T12:16:37.178Z","title":"支付","icon":null,"ownVisible":null,"nav":[{"name":"支付乐","createdAt":"2022-11-18T12:32:58.999Z","rate":5,"desc":"免签约支付平台","top":false,"ownVisible":false,"icon":null,"url":"http://www.zhifule.cn/","urls":{}},{"name":"虎皮椒支付","createdAt":"2022-11-18T12:27:57.305Z","rate":4.5,"desc":"免签约支付平台","top":false,"ownVisible":false,"icon":"https://www.xunhupay.com/wp-content/themes/hupijiao/favicon.ico","url":"https://www.xunhupay.com/","urls":{}},{"name":"ZFBJK","createdAt":"2022-11-18T12:24:48.530Z","rate":4.5,"desc":"支付宝免签约,宣称9年老品牌","top":false,"ownVisible":false,"icon":null,"url":"https://www.zfbjk.com/","urls":{}},{"name":"即充宝","createdAt":"2022-11-18T12:19:45.193Z","rate":4.5,"desc":"免签约支付平台","top":false,"ownVisible":false,"icon":null,"url":"http://jfbpay.com/","urls":{}}]}]}],"id":1}]